LICENSE.txt
MANIFEST.in
README.rst
setup.py
roscraco/__init__.py
roscraco/exception.py
roscraco.egg-info/PKG-INFO
roscraco.egg-info/SOURCES.txt
roscraco.egg-info/dependency_links.txt
roscraco.egg-info/top_level.txt
roscraco/helper/__init__.py
roscraco/helper/converter.py
roscraco/helper/validator.py
roscraco/response/__init__.py
roscraco/response/clients.py
roscraco/response/dhcp.py
roscraco/response/dmz.py
roscraco/response/info.py
roscraco/response/stats.py
roscraco/response/wireless.py
roscraco/router/__init__.py
roscraco/router/base.py
roscraco/router/canyon/__init__.py
roscraco/router/canyon/cnpwf514n1.py
roscraco/router/canyon/cnpwf518n3.py
roscraco/router/canyon/cnwf514.py
roscraco/router/netgear/__init__.py
roscraco/router/netgear/wgr614.py
roscraco/router/tenda/__init__.py
roscraco/router/tenda/w268r.py
roscraco/router/tomato/__init__.py
roscraco/router/tomato/v1_23.py
roscraco/router/tplink/__init__.py
roscraco/router/tplink/base.py
roscraco/router/tplink/wr340g.py
roscraco/router/tplink/wr720n.py
roscraco/router/tplink/wr740n.py
roscraco/router/tplink/wr741n.py
roscraco/router/tplink/wr940n.py
roscraco/router/tplink/wr941n.py
roscraco/router/zyxel/__init__.py
roscraco/router/zyxel/p320w.py
roscraco/router/zyxel/p330w.py