Metadata-Version: 1.1
Name: roscraco
Version: 0.4.0
Summary: A library for managing home routers (networking equipment).
Home-page: https://github.com/spantaleev/roscraco
Author: Slavi Pantaleev
Author-email: s.pantaleev@gmail.com
License: BSD
Keywords: router,networking,tplink,canyon,netgear,zyxel,tomato
Platform: any
Classifier: Programming Language :: Python
Classifier: Programming Language :: Python :: 2.6
Classifier: Programming Language :: Python :: 2.7
Classifier: Programming Language :: Python :: 3.4
Classifier: Development Status :: 4 - Beta
Classifier: Environment :: Console
Classifier: Intended Audience :: Developers
Classifier: Intended Audience :: Telecommunications Industry
Classifier: Intended Audience :: System Administrators
Classifier: License :: OSI Approved :: BSD License
Classifier: Operating System :: OS Independent
Classifier: Topic :: Internet :: WWW/HTTP :: Dynamic Content
Classifier: Topic :: System :: Networking
Classifier: Topic :: Home Automation
Classifier: Topic :: Software Development :: Libraries :: Python Modules
